pyBIG/__init__.py
pyBIG/base_archive.py
pyBIG/disk_archive.py
pyBIG/memory_archive.py
pyBIG/refpack.py
pybig-0.6.6.dist-info/licenses/LICENSE
pybig-0.6.6.dist-info/METADATA
pybig-0.6.6.dist-info/WHEEL
pybig-0.6.6.dist-info/top_level.txt
pybig-0.6.6.dist-info/RECORD
